.gitignore
LICENSE
MANIFEST.in
README.rst
setup.py
mkpip/__init__.py
mkpip/bin.py
mkpip/bumpy.py
mkpip/config.py
mkpip/mkbin.py
mkpip/mkmod.py
mkpip.egg-info/PKG-INFO
mkpip.egg-info/SOURCES.txt
mkpip.egg-info/dependency_links.txt
mkpip.egg-info/entry_points.txt
mkpip.egg-info/requires.txt
mkpip.egg-info/top_level.txt
mkpip/.ropeproject/config.py
mkpip/boilerplate/setup.pyt
mkpip/boilerplate/tests/test_{name}.pyt
mkpip/boilerplate/{name}/__init__.pyt
mkpip/templates/bin.py
mkpip/templates/.ropeproject/config.py