Metadata-Version: 1.1
Name: mkpip
Version: 0.9.3
Summary: mkpip
Home-page: https://bitbucket.org/johannestaas/mkpip
Author: Johan Nestaas
Author-email: johannestaas@gmail.com
License: GPLv3+
Keywords: pip python package pypi
Platform: UNKNOWN
Classifier: Development Status :: 3 - Alpha
Classifier: License :: OSI Approved :: GNU General Public License v3 or later (GPLv3+)
Classifier: Environment :: Console
Classifier: Environment :: X11 Applications :: Qt
Classifier: Environment :: MacOS X
Classifier: Environment :: Win32 (MS Windows)
Classifier: Operating System :: POSIX
Classifier: Operating System :: MacOS :: MacOS X
Classifier: Operating System :: Microsoft :: Windows
Classifier: Programming Language :: Python
Classifier: Topic :: Utilities
